<?xml version="1.0" standalone="yes"?>  <DATAPACKET Version="2.0"><METADATA><FIELDS><FIELD attrname="CEP" fieldtype="string" WIDTH="20"/><FIELD attrname="LOGRADOURO" fieldtype="string" WIDTH="200"/><FIELD attrname="NUMERO" fieldtype="string" WIDTH="30"/><FIELD attrname="COMPLEMENTO" fieldtype="string" WIDTH="30"/><FIELD attrname="BAIRRO" fieldtype="string" WIDTH="100"/><FIELD attrname="CIDADE" fieldtype="string" WIDTH="100"/><FIELD attrname="ESTADO" fieldtype="string" WIDTH="2"/><FIELD attrname="PAIS" fieldtype="string" WIDTH="100"/><FIELD attrname="CPF" fieldtype="string" WIDTH="15"/></FIELDS><PARAMS CHANGE_LOG="1 0 4"/></METADATA><ROWDATA><ROW RowState="4" CEP="33600-000" LOGRADOURO="rua comendador antonio alves" NUMERO="90" COMPLEMENTO="apto" BAIRRO="b" CIDADE="Pedro Leopoldo" ESTADO="MG" PAIS="brasil" CPF="05496621623"/></ROWDATA></DATAPACKET>